pgdoc_datatype_parser/__init__.py
pgdoc_datatype_parser/pg-releases.json
pgdoc_datatype_parser-2.0.0.dist-info/LICENSE
pgdoc_datatype_parser-2.0.0.dist-info/METADATA
pgdoc_datatype_parser-2.0.0.dist-info/WHEEL
pgdoc_datatype_parser-2.0.0.dist-info/top_level.txt
pgdoc_datatype_parser-2.0.0.dist-info/zip-safe
pgdoc_datatype_parser-2.0.0.dist-info/RECORD
